notochord/__init__.py
notochord/__main__.py
notochord/app/__init__.py
notochord/app/harmonizer.css
notochord/app/harmonizer.py
notochord/app/homunculus.css
notochord/app/homunculus.py
notochord/app/homunculus.toml
notochord/app/improviser.css
notochord/app/improviser.py
notochord/app/morse.py
notochord/app/preset-zeno.toml
notochord/app/prompt.py
notochord/app/server.py
notochord/app/simple_harmonizer.py
notochord/app/txalaparta.py
notochord/data.py
notochord/distributions.py
notochord/model.py
notochord/perform.py
notochord/rnn.py
notochord/train.py
notochord/util.py
notochord-0.7.5.dist-info/LICENSE
notochord-0.7.5.dist-info/METADATA
notochord-0.7.5.dist-info/WHEEL
notochord-0.7.5.dist-info/entry_points.txt
notochord-0.7.5.dist-info/RECORD
