Metadata-Version: 2.1
Name: notochord
Version: 0.7.5
Summary: Notochord is a real-time neural network model for MIDI performances.
License: MIT
Author: Victor Shepardson
Author-email: victor.shepardson@gmail.com
Requires-Python: >=3.10,<3.14
Classifier: License :: OSI Approved :: MIT License
Classifier: Programming Language :: Python :: 3
Classifier: Programming Language :: Python :: 3.10
Classifier: Programming Language :: Python :: 3.11
Classifier: Programming Language :: Python :: 3.12
Provides-Extra: morse
Provides-Extra: train
Requires-Dist: appdirs (>=1.4.4,<2.0.0)
Requires-Dist: audioop-lts ; python_version >= "3.13"
Requires-Dist: iipyper (>=0.4.0,<0.5.0)
Requires-Dist: joblib (>=1.4.2,<2.0.0)
Requires-Dist: numpy (>=1.23,<3)
Requires-Dist: pandas (>=2.0,<3.0)
Requires-Dist: sf2utils (>=1.0.0,<2.0.0)
Requires-Dist: tensorboard (>=2.17.1,<3.0.0) ; extra == "train"
Requires-Dist: toml-file (>=1.0.5,<2.0.0)
Requires-Dist: torch (>=1.13,<2.7)
Requires-Dist: tqdm (>=4.64,<5.0)
Requires-Dist: transformers (>=4.39,<4.40) ; extra == "morse"
